{
    "configurations": [
        {
            "name": "Win64",
            "defines": [
                "_DEBUG",
                "UNICODE",
                "_UNICODE"
            ],
            "compilerPath": "g++.exe",
            "cStandard": "c11",
            "intelliSenseMode": "gcc-x64",
            "cppStandard": "c++20",
            "includePath": [
                "lib/SFML/include",
                "lib/lodepng",
                "lib/SDL-1.2.15/include",
				"World",
				"World/Map",
				"World/Map/Sector",
				"Entities",
				"Entities/Interfaces",
				"Entities/Models",
				"Entities/Projectiles",
				"Control",
				"Control/Controllers",
				"Control/Actions",
				"Control/AI",
                "Control/Player",
                "Control/Projectile",
				"UI",
				"UI/DisplayDriver",
				"UI/ControllerDriver",
				"Menu",
                "utils"
            ]
        }
    ],
    "version": 4
}